aiowolfram/__init__.py
aiowolfram/aiowolfram.py
aiowolfram-1.0.3.dist-info/METADATA
aiowolfram-1.0.3.dist-info/RECORD
aiowolfram-1.0.3.dist-info/WHEEL
aiowolfram-1.0.3.dist-info/top_level.txt
