Metadata-Version: 2.1
Name: aiowolfram
Version: 1.0.3
Summary: an async wrapper for wolfram-alphas web api
Home-page: https://github.com/Apache-HB/aiowolfram
Author: Elliot Haisley
Author-email: apachehb@gmail.com
License: Apache2.0
Keywords: wolfram,wolframalpha,wolfram-alpha,async,json
Platform: UNKNOWN
Requires-Dist: aiohttp
